akratiaccount/__init__.py
akratiaccount-0.1.dist-info/License.txt
akratiaccount-0.1.dist-info/METADATA
akratiaccount-0.1.dist-info/WHEEL
akratiaccount-0.1.dist-info/top_level.txt
akratiaccount-0.1.dist-info/RECORD
